[
    {
        "ID": "#4794", 
        "Date": "30/10/2022",
        "Value": "R$ 125,90",
        "Status": "Concluído"
       
    },
    {
        "ID": "#4798", 
        "Date": "31/10/2022",
        "Value": "R$ 13,90",
        "Status": "Concluído"
       
    },
    {
        "ID": "#4820", 
        "Date": "02/11/2022",
        "Value": "R$ 47,90",
        "Status": "Pendente"
       
    },
    {
        "ID": "#4835", 
        "Date": "03/11/2022",
        "Value": "R$ 79,00",
        "Status": "Cancelado"
        
    },
    {
        "ID": "#4840", 
        "Date": "03/11/2022",
        "Value": "R$ 112,55",
        "Status": "Concluído"
    
    },   
     {
        "ID": "#4855", 
        "Date": "04/11/2022",
        "Value": "R$ 55,35",
        "Status": "Pendente"
        
    },    
    {
        "ID": "#4876", 
        "Date": "06/11/2022",
        "Value": "R$ 230,50",
        "Status": "Concluído"
        
    },    
    {
        "ID": "#4890", 
        "Date": "08/11/2022",
        "Value": "R$ 50,90",
        "Status": "Cancelado"
        
    }
]